homepage/README.md
homepage/__init__.py
homepage/admin.py
homepage/apps.py
homepage/models.py
homepage/urls.py
homepage/views.py
homepage/migrations/0001_initial.py
homepage/migrations/__init__.py
homepage/static/homepage/css/css.css
homepage/static/homepage/css/font-awesome.min.css
homepage/static/homepage/css/icon.css
homepage/static/homepage/css/site.css
homepage/static/homepage/img/1zlab-logo-with-words.png
homepage/static/homepage/img/1zlab-logo.png
homepage/static/homepage/img/1zlab-logo.svg
homepage/static/homepage/img/1zlab-qq-qrcode.jpg
homepage/static/homepage/img/background-mobile.png
homepage/static/homepage/img/background.png
homepage/static/homepage/img/ide.png
homepage/static/homepage/js/vue-index.js
homepage/templates/homepage/index.html
homepage/templates/homepage/robots.txt
homepage/templates/homepage/sitemap.xml
1zlab_homepage-0.0.3.dist-info/AUTHORS
1zlab_homepage-0.0.3.dist-info/METADATA
1zlab_homepage-0.0.3.dist-info/WHEEL
1zlab_homepage-0.0.3.dist-info/pbr.json
1zlab_homepage-0.0.3.dist-info/top_level.txt
1zlab_homepage-0.0.3.dist-info/RECORD
